geckocheck/__init__.py
geckocheck/main.py
geckocheck-1.0.0.dist-info/LICENSE
geckocheck-1.0.0.dist-info/METADATA
geckocheck-1.0.0.dist-info/WHEEL
geckocheck-1.0.0.dist-info/entry_points.txt
geckocheck-1.0.0.dist-info/top_level.txt
geckocheck-1.0.0.dist-info/RECORD
